MANIFEST.in
VERSION
requirements.txt
setup.py
demo/requirements.txt
src/luminol/__init__.py
src/luminol/anomaly_detector.py
src/luminol/constants.py
src/luminol/correlator.py
src/luminol/exceptions.py
src/luminol/utils.py
src/luminol.egg-info/PKG-INFO
src/luminol.egg-info/SOURCES.txt
src/luminol.egg-info/dependency_links.txt
src/luminol.egg-info/requires.txt
src/luminol.egg-info/top_level.txt
src/luminol/algorithms/__init__.py
src/luminol/algorithms/anomaly_detector_algorithms/__init__.py
src/luminol/algorithms/anomaly_detector_algorithms/absolute_threshold.py
src/luminol/algorithms/anomaly_detector_algorithms/all.py
src/luminol/algorithms/anomaly_detector_algorithms/bitmap_detector.py
src/luminol/algorithms/anomaly_detector_algorithms/default_detector.py
src/luminol/algorithms/anomaly_detector_algorithms/derivative_detector.py
src/luminol/algorithms/anomaly_detector_algorithms/diff_percent_threshold.py
src/luminol/algorithms/anomaly_detector_algorithms/exp_avg_detector.py
src/luminol/algorithms/anomaly_detector_algorithms/sign_test.py
src/luminol/algorithms/correlator_algorithms/__init__.py
src/luminol/algorithms/correlator_algorithms/all.py
src/luminol/algorithms/correlator_algorithms/cross_correlator.py
src/luminol/modules/__init__.py
src/luminol/modules/anomaly.py
src/luminol/modules/correlation_result.py
src/luminol/modules/time_series.py