Metadata-Version: 1.0
Name: luminol
Version: 0.3.1
Summary: luminol is an anomaly detection and correlation library for timeseries data.
Home-page: https://github.com/linkedin/luminol
Author: Naarad Developers
Author-email: naarad-dev@googlegroups.com
License: Apache 2.0
Platform: UNKNOWN
